{
    "filterGroups":[
        {
            "file":"lsq_filter_Beauty_1.gfilter",
            "name":"lsq_filter_group_Beauty",
            "default_filter_id":1,
            "filters":[
                {
                    "id":1,
                    "name":"lsq_filter_SkinNature",
                    "color":"#E9807E",
                    "args":{
                        "smoothing":0.7,
                        "mixied":1
                    }
                },
                {
                    "id":2,
                    "name":"lsq_filter_SkinPink",
                    "color":"#E9807E",
                    "args":{
                        "smoothing":0.7,
                        "mixied":0.75
                    }
                },
                {
                    "id":3,
                    "name":"lsq_filter_SkinJelly",
                    "color":"#E9807E",
                    "args":{
                        "smoothing":0.7,
                        "mixied":0.75
                    }
                },
                {
                    "id":4,
                    "name":"lsq_filter_SkinRuddy",
                    "color":"#E9807E",
                    "args":{
                        "smoothing":0.7,
                        "mixied":0.75
                    }
                },
                {
                    "id":5,
                    "name":"lsq_filter_SkinSugar",
                    "color":"#E9807E",
                    "args":{
                        "smoothing":0.7,
                        "mixied":0.75
                    }
                },
                {
                    "id":6,
                    "name":"lsq_filter_SkinPowder",
                    "color":"#E9807E",
                    "args":{
                        "smoothing":0.7,
                        "mixied":0.75
                    }
                },
                {
                    "id":7,
                    "name":"lsq_filter_SkinNoir",
                    "color":"#E9807E",
                    "args":{
                        "smoothing":0.7,
                        "mixied":1
                    }
                }
            ]
        },
        {
            "file":"lsq_filter_MeituBeauty_2.gfilter",
            "name":"lsq_filter_group_MeituBeauty",
            "default_filter_id":8,
            "filters":[
                {
                    "id":8,
                    "name":"lsq_filter_Nature",
                    "color":"#E9807E",
                    "args":{
                        "smoothing":1,
                        "mixied":1,
                        "whitening":0
                    }
                },
                {
                    "id":9,
                    "name":"lsq_filter_Blusher",
                    "color":"#E9807E",
                    "args":{
                        "smoothing":1,
                        "mixied":1,
                        "whitening":0.3
                    }
                },
                {
                    "id":10,
                    "name":"lsq_filter_Jelly",
                    "color":"#E9807E",
                    "args":{
                        "smoothing":1,
                        "mixied":0.8,
                        "whitening":0
                    }
                },
                {
                    "id":11,
                    "name":"lsq_filter_Ruddy",
                    "color":"#E9807E",
                    "args":{
                        "smoothing":1,
                        "mixied":1,
                        "whitening":0
                    }
                },
                {
                    "id":12,
                    "name":"lsq_filter_Sugar",
                    "color":"#E9807E",
                    "args":{
                        "smoothing":1,
                        "mixied":0.75,
                        "whitening":0
                    }
                },
                {
                    "id":13,
                    "name":"lsq_filter_Powder",
                    "color":"#E9807E",
                    "args":{
                        "smoothing":1,
                        "mixied":1,
                        "whitening":0.24
                    }
                },
                {
                    "id":14,
                    "name":"lsq_filter_Whitening",
                    "color":"#dfaea7",
                    "args":{
                        "smoothing":1,
                        "mixied":1,
                        "whitening":0.8
                    }
                },
                {
                    "id":15,
                    "name":"lsq_filter_Jam",
                    "color":"#E9807E",
                    "args":{
                        "smoothing":1,
                        "mixied":1,
                        "whitening":0
                    }
                }
            ]
        },
        {
            "file":"lsq_filter_Leica_3.gfilter",
            "name":"lsq_filter_group_Leica",
            "default_filter_id":16,
            "filters":[
                {
                    "id":16,
                    "name":"lsq_filter_Brilliant",
                    "color":"#E74C3C",
                    "args":{
                        "mixied":0.5
                    }
                },
                {
                    "id":17,
                    "name":"lsq_filter_Leica",
                    "color":"#E74C3C",
                    "args":{
                        "mixied":0.6
                    }
                },
                {
                    "id":18,
                    "name":"lsq_filter_Gloss",
                    "color":"#E74C3C",
                    "args":{
                        "mixied":0.55
                    }
                },
                {
                    "id":19,
                    "name":"lsq_filter_Harmony",
                    "color":"#E74C3C",
                    "args":{
                        "mixied":0.75
                    }
                },
                {
                    "id":20,
                    "name":"lsq_filter_Noir",
                    "color":"#E74C3C"
                }
            ]
        },
        {
            "file":"lsq_filter_Food_4.gfilter",
            "name":"lsq_filter_group_Food",
            "default_filter_id":21,
            "filters":[
                {
                    "id":21,
                    "name":"lsq_filter_Sweet",
                    "color":"#18BC9C",
                    "args":{
                        "mixied":0.7,
                        "vignette":0.5
                    }
                },
                {
                    "id":22,
                    "name":"lsq_filter_Thick",
                    "color":"#18BC9C",
                    "args":{
                        "mixied":0.7,
                        "vignette":0.6
                    }
                },
                {
                    "id":23,
                    "name":"lsq_filter_Coffee",
                    "color":"#18BC9C",
                    "args":{
                        "mixied":0.7,
                        "vignette":0.6
                    }
                },
                {
                    "id":24,
                    "name":"lsq_filter_Gold",
                    "color":"#18BC9C",
                    "args":{
                        "mixied":1,
                        "vignette":0.6
                    }
                },
                {
                    "id":25,
                    "name":"lsq_filter_Rum",
                    "color":"#18BC9C",
                    "args":{
                        "mixied":0.7,
                        "vignette":0.6
                    }
                }
            ]
        },
        {
            "file":"lsq_filter_Enhance_5.gfilter",
            "name":"lsq_filter_group_Enhance",
            "default_filter_id":26,
            "filters":[
                {
                    "id":26,
                    "name":"lsq_filter_Cheerful",
                    "color":"#7E6B5A",
                    "args":{
                        "mixied":0.75
                    }
                },
                {
                    "id":27,
                    "name":"lsq_filter_Lightup",
                    "color":"#7E6B5A",
                    "args":{
                        "mixied":0.85
                    }
                },
                {
                    "id":28,
                    "name":"lsq_filter_Relaxed",
                    "color":"#7E6B5A",
                    "args":{
                        "mixied":0.6
                    }
                },
                {
                    "id":29,
                    "name":"lsq_filter_Rough",
                    "color":"#7E6B5A",
                    "args":{
                        "mixied":0.55
                    }
                },
                {
                    "id":30,
                    "name":"lsq_filter_Instant",
                    "color":"#7E6B5A",
                    "args":{
                        "mixied":0.5
                    }
                }
            ]
        },
        {
            "file":"lsq_filter_Glare_6.gfilter",
            "name":"lsq_filter_group_Glare",
            "default_filter_id":31,
            "filters":[
                {
                    "id":31,
                    "name":"lsq_filter_Winter",
                    "color":"#FFA500",
                    "args":{
                        "mixied":0.8
                    }
                },
                {
                    "id":32,
                    "name":"lsq_filter_Coloration",
                    "color":"#FFA500",
                    "args":{
                        "mixied":0.8
                    }
                },
                {
                    "id":33,
                    "name":"lsq_filter_Fluorescent",
                    "color":"#FFA500",
                    "args":{
                        "mixied":0.8
                    }
                },
                {
                    "id":34,
                    "name":"lsq_filter_Freshmorning",
                    "color":"#FFA500",
                    "args":{
                        "mixied":0.8
                    }
                },
                {
                    "id":35,
                    "name":"lsq_filter_Holidaysunshine",
                    "color":"#FFA500",
                    "args":{
                        "mixied":0.8
                    }
                },
                {
                    "id":36,
                    "name":"lsq_filter_Purplemoon",
                    "color":"#FFA500",
                    "args":{
                        "mixied":0.8
                    }
                },
                {
                    "id":37,
                    "name":"lsq_filter_Summer",
                    "color":"#FFA500",
                    "args":{
                        "mixied":0.8
                    }
                }
            ]
        },
        {
            "file":"lsq_filter_EdgeEffects_7.gfilter",
            "name":"lsq_filter_group_EdgeEffects",
            "default_filter_id":43,
            "filters":[
                {
                    "id":43,
                    "name":"lsq_filter_Starshine",
                    "color":"#0cfff3",
                    "args":{
                        "edgeStrength":0.35,
                        "speed":0.3,
                        "showType":0.15
                    }
                },
                {
                    "id":44,
                    "name":"lsq_filter_Fluorescence",
                    "color":"#20fdad",
                    "args":{
                        "edgeStrength":0.35,
                        "speed":0.3,
                        "showType":0.3
                    }
                },
                {
                    "id":45,
                    "name":"lsq_filter_Infrared",
                    "color":"#ff8f00",
                    "args":{
                        "edgeStrength":0.35,
                        "speed":0.3,
                        "showType":0.5
                    }
                },
                {
                    "id":46,
                    "name":"lsq_filter_Azure",
                    "color":"#5a62ff",
                    "args":{
                        "edgeStrength":0.35,
                        "speed":0.48,
                        "showType":1
                    }
                },
                {
                    "id":47,
                    "name":"lsq_filter_Multicolor",
                    "color":"#50afff",
                    "args":{
                        "edgeStrength":0.35,
                        "speed":0.3,
                        "showType":0.5
                    }
                }
            ]
        },
        {
            "file":"lsq_filter_Mottle_9.gfilter",
            "name":"lsq_filter_group_Mottle",
            "default_filter_id":48,
            "filters":[
                {
                    "id":48,
                    "name":"lsq_filter_Time",
                    "color":"#a39369",
                    "args":{
                        "mixied":1,
                        "texture":0.1,
                        "vignette":0.75
                    }
                },
                {
                    "id":49,
                    "name":"lsq_filter_Recall",
                    "color":"#a39369",
                    "args":{
                        "mixied":1,
                        "texture":0.24,
                        "vignette":0.6
                    }
                },
                {
                    "id":50,
                    "name":"lsq_filter_Yellowing",
                    "color":"#a39369",
                    "args":{
                        "mixied":1,
                        "texture":0.2,
                        "vignette":0.6
                    }
                },
                {
                    "id":51,
                    "name":"lsq_filter_Years",
                    "color":"#a39369",
                    "args":{
                        "mixied":1,
                        "texture":0.1,
                        "vignette":0.5
                    }
                },
                {
                    "id":52,
                    "name":"lsq_filter_Age",
                    "color":"#a39369",
                    "args":{
                        "mixied":1,
                        "texture":0.14,
                        "vignette":0.6
                    }
                }
            ]
        }
    ],
    "stickerCategories":[
        {
            "id":1,
            "name":"Sticker"
        },
        {
            "id":2,
            "name":"Mood"
        },
        {
            "id":3,
            "name":"Watermarking"
        }
    ],
    "stickerGroups":[
        {
            "file":"lsq_sticker_1_31.gsce",
            "name":"Butterfly",
            "stickers":[
                {
                    "id":239
                },
                {
                    "id":240
                },
                {
                    "id":241
                },
                {
                    "id":242
                },
                {
                    "id":243
                },
                {
                    "id":244
                },
                {
                    "id":245
                },
                {
                    "id":246
                },
                {
                    "id":247
                },
                {
                    "id":248
                },
                {
                    "id":249
                },
                {
                    "id":250
                }
            ]
        },
        {
            "file":"lsq_sticker_1_30.gsce",
            "name":"Weather",
            "stickers":[
                {
                    "id":231
                },
                {
                    "id":232
                },
                {
                    "id":233
                },
                {
                    "id":234
                },
                {
                    "id":235
                },
                {
                    "id":236
                },
                {
                    "id":237
                },
                {
                    "id":238
                }
            ]
        },
        {
            "file":"lsq_sticker_1_16.gsce",
            "name":"Corgi",
            "stickers":[
                {
                    "id":119
                },
                {
                    "id":120
                },
                {
                    "id":121
                },
                {
                    "id":122
                },
                {
                    "id":123
                },
                {
                    "id":124
                },
                {
                    "id":125
                },
                {
                    "id":126
                }
            ]
        },
        {
            "file":"lsq_sticker_2_10.gsce",
            "name":"Expression",
            "stickers":[
                {
                    "id":63
                },
                {
                    "id":64
                },
                {
                    "id":65
                },
                {
                    "id":66
                },
                {
                    "id":67
                },
                {
                    "id":68
                },
                {
                    "id":69
                },
                {
                    "id":70
                },
                {
                    "id":71
                },
                {
                    "id":72
                },
                {
                    "id":73
                },
                {
                    "id":74
                }
            ]
        },
        {
            "file":"lsq_sticker_1_5.gsce",
            "name":"Chicken",
            "stickers":[
                {
                    "id":29
                },
                {
                    "id":30
                },
                {
                    "id":31
                },
                {
                    "id":32
                },
                {
                    "id":33
                },
                {
                    "id":34
                },
                {
                    "id":35
                },
                {
                    "id":36
                }
            ]
        },
        {
            "file":"lsq_sticker_1_4.gsce",
            "name":"Dog",
            "stickers":[
                {
                    "id":17
                },
                {
                    "id":18
                },
                {
                    "id":19
                },
                {
                    "id":20
                },
                {
                    "id":21
                },
                {
                    "id":22
                },
                {
                    "id":23
                },
                {
                    "id":24
                },
                {
                    "id":25
                },
                {
                    "id":26
                },
                {
                    "id":27
                },
                {
                    "id":28
                }
            ]
        },
        {
            "file":"lsq_sticker_1_3.gsce",
            "name":"Alpaca",
            "stickers":[
                {
                    "id":9
                },
                {
                    "id":10
                },
                {
                    "id":11
                },
                {
                    "id":12
                },
                {
                    "id":13
                },
                {
                    "id":14
                },
                {
                    "id":15
                },
                {
                    "id":16
                }
            ]
        }
    ],
    "brushGroups":[
        {
            "file":"lsq_brush_default.gbsh",
            "name":"default",
            "brushes":[
                {
                    "id":1,
                    "name":"lsq_brush_Gouache"
                },
                {
                    "id":2,
                    "name":"lsq_brush_MapleLeaf"
                },
                {
                    "id":3,
                    "name":"lsq_brush_Mosaic"
                },
                {
                    "id":4,
                    "name":"lsq_brush_OilPaint"
                },
                {
                    "id":5,
                    "name":"lsq_brush_WaterColor"
                },
                {
                    "id":6,
                    "name":"lsq_brush_ColorLead"
                }
            ]
        }
    ],
    "master":"tDBvmB7nI6WztKuL9mGBB9Mrnm9JFZoQ2nnwMXdtLTWYxI1JWaq9edgQnaLKA2T+FoicUKWoa0wzKvnqWR6yHdSOC3VUwd+eDH8Vff+7Wp05eYZGvTFXf\/KyDE1c8t+dY9GL3v\/wOG5ECbD0R4dOhcitSLWWeT0MLRcb3N\/cN9nvc128+9mYrxTQgOhU+C9YT4KBuXovpGoG0QMbzNN2C0ljRwHrK\/ELsyBv5npftJvy+TpHUr1Xcn\/1NlSMZEAnJBpwrT2mjeTrJzDAHTCp691OhToSvghtehwHJyglWmmM1sZHG0+Jy64ezBwHKNK3i3\/v46fviiagsraLMUWYYB4GXKOidRYi9imlQnZWhdxRWDJLDUFBkTGOJzxzucSu3VLx421xOY+vwWgVqLUx2sMLvuc6xAeKdqwyReoHIICswGF6x2pstkWWPvRB2HrvpALIcmaNWtddNCwm1mYNGC9DG1FJ8rNEVFZLLvdesz4n1fG37fgdCQbHlMJNvGC8utcFZKJfcmLa8VRpHtiCurSDSs2du9coicELDtQMtgZs+vPnXtFTl7cncd\/cQ+PMk8tot2fi99U11FVJZl7yrKngAfvOrWYJB7lMaAU5npCUHlg70dvsai\/zr+KfGkNvFX7EOzYfsuCczWcfG2+osXKnd0\/FISVvvz\/QMAEsybzGMPsIed9ZO\/5UZW46jV3cV4TFxAMiNDbxhOB3gH5twvXKDF3uhrXL8HSLt15VLTGA4Qsjl40ytu+d869fMINBphpb6s4JPo4+a9qPOuggU2zQSVvfBT+4IWqQ+0IfrA4NsonJbTbkO9z1bRBW9reaiNZa4nc5AzYflOs9C1HqzQ4qyrGxnLkcPr6J0jQxO+D2V62iMrtvj10xDxihM3Nath8AuM2lO5UF1GlEmlD0aqM+jeBxotDPjoVTaGwe3TkoiQKbOZ1kpAlD+9jqNwjSdPDUVxBJh2J9E3M4XwTplDpig0yXbioJhFZ9LjWKvzEHZ9JUkw0FjtWoEw4gD8VlIIT1ejq\/5hP\/KYs371bfnxIAaCR8gVkY+2UEc\/iPb2PQrEougpnSThk3c91b6cs08UUS9YlzPlpUEm4oEgRONyoYGsQ\/agb\/e5LFC6fD2BAXBg0X+VaibQcu2YQx8nZrw8KbB77VGEAg9j3BhUrSLbDj7bZrC4F7bQSS+9TC+XAZIw7CUHVJk9j2fNJci+6eEzCyWeehWFSUfYu7rWIN\/4s13qS4nLd3VZj7gduJJjms\/p0dXyb7fHXRdRtvAtmeVSRS+8vUVljOguilXhdk6JpwJ6HxZ5rSSgd99cZz3kqb\/hqyrWSS4iXqFxyg5agjksbxsFs9aVYRenR2WYAxaSHhiPmHABgEtdhyOglnsRu78yhqPLW0JhSag2iaDrIHpPFiuvXfVBLCVZshwZLkTMp4ZS8Fal5ywKUTOAqJwqHSrRqReFXSF1bBhWpw\/WGX146jCnFiFAHw9igBj5AheFYmiMpwHbRZe81E4qwy7VchRUjQUPC\/SchIJ8WcitNGsbyZlgqkIC4lvEAtItIZfUMwIEkdUGSwZSoxI51U4XQwf0l+NkhR8kD5F3tS99YHR2A5huKiVMmAKweAreAoJ8a2FVDYE020spgYlOCOxxodhtxxduYDgeyvvp0uvsiV6xmuvcHGMhuxeDcc6Jl6k2XsP0xcxnSfV4FxfOLdzp9LMo3sIiiUUmNb+K+QMqM+F3xt0\/yv2DdmPYokMPAePc9cis5fx2d0wDnYqb8TpNuMwosz68nZwTlfVUeAeWID7529A06908"
}